setup.py
blob_app/__init__.py
blob_app/blob_commands.py
blob_app/blob_facade.py
blob_app/blob_model.py
blob_app.egg-info/PKG-INFO
blob_app.egg-info/SOURCES.txt
blob_app.egg-info/dependency_links.txt
blob_app.egg-info/not-zip-safe
blob_app.egg-info/requires.txt
blob_app.egg-info/top_level.txt
test/testloader.py