Metadata-Version: 1.1
Name: blob-app
Version: 0.3
Summary: A Tekton's app to handle file download and upload
Home-page: https://github.com/renzon/blob_app
Author: Renzo Nuccitelli
Author-email: renzo.n@gmail.com
License: MIT
Platform: UNKNOWN
Classifier: Development Status :: 4 - Beta
Classifier: Environment :: Web Environment
Classifier: Intended Audience :: Developers
Classifier: License :: OSI Approved :: BSD License
Classifier: Operating System :: OS Independent
Classifier: Programming Language :: Python
Classifier: Framework :: Paste
